{
    "summary": {
        "all_emails": [
            "civil.design.team@infraplan.in",
            "newemail@gmail.com",
            "shubham2@gmail.com",
            "shubham@gmail.com",
            "support.projects@urbanflow.net",
            "testemail@gmail.com"
        ],
        "all_phones": [
            "02026547891",
            "8520369852",
            "8563256325",
            "9876012345"
        ],
        "all_addresses": []
    },
    "folders": [
        {
            "folder": "Extract-Emails-from-Files",
            "files": [
                {
                    "file_name": "File5.pdf.txt",
                    "emails": [
                        "civil.design.team@infraplan.in",
                        "newemail@gmail.com",
                        "shubham2@gmail.com",
                        "shubham@gmail.com",
                        "support.projects@urbanflow.net",
                        "testemail@gmail.com"
                    ],
                    "phones": [
                        "02026547891",
                        "8520369852",
                        "8563256325",
                        "9876012345"
                    ],
                    "addresses": []
                },
                {
                    "file_name": "File5.pdf.txt",
                    "emails": [
                        "civil.design.team@infraplan.in",
                        "newemail@gmail.com",
                        "shubham2@gmail.com",
                        "shubham@gmail.com",
                        "support.projects@urbanflow.net",
                        "testemail@gmail.com"
                    ],
                    "phones": [
                        "02026547891",
                        "8520369852",
                        "8563256325",
                        "9876012345"
                    ],
                    "addresses": []
                }
            ]
        },
        {
            "folder": "setuptools-58.1.0.dist-info",
            "files": [
                {
                    "file_name": "top_level.txt",
                    "emails": [],
                    "phones": [],
                    "addresses": []
                }
            ]
        }
    ]
}